fmtr/__init__.py
fmtr-0.0.0.dist-info/METADATA
fmtr-0.0.0.dist-info/WHEEL
fmtr-0.0.0.dist-info/top_level.txt
fmtr-0.0.0.dist-info/RECORD
