Metadata-Version: 2.1
Name: fmtr
Version: 0.0.0
Summary: Coming soon
Author-email: Frontmatter <frisky.sanchez@mask.pro.fmtr.dev>
